bitwarden_sdk-1.0.0.dist-info/METADATA
bitwarden_sdk-1.0.0.dist-info/WHEEL
bitwarden_sdk-1.0.0.dist-info/licenses/LICENSE
bitwarden_sdk/bitwarden_client.py
bitwarden_sdk/schemas.py
bitwarden_sdk/__init__.py
bitwarden_py/__init__.py
bitwarden_py/bitwarden_py.cpython-312-x86_64-linux-gnu.so
bitwarden_sdk-1.0.0.dist-info/RECORD
