Metadata-Version: 2.3
Name: bitwarden_sdk
Version: 1.0.0
Classifier: Development Status :: 4 - Beta
Classifier: Intended Audience :: Developers
Classifier: License :: Other/Proprietary License
Classifier: Programming Language :: Python :: 3 :: Only
Classifier: Programming Language :: Rust
Classifier: Topic :: Security
Requires-Dist: dateutils >=0.6.6
License-File: LICENSE
Summary: A Bitwarden Client for python
Keywords: bitwarden
Home-Page: https://bitwarden.com
Author: Bitwarden Inc
Author-email: Bitwarden <support@bitwarden.com>
Requires-Python: >=3.0
Project-URL: Source Code, https://github.com/bitwarden/sdk
